pyGPT_api/__init__.py
pyGPT_api/errors.py
pyGPT_api-0.1.3.dist-info/METADATA
pyGPT_api-0.1.3.dist-info/WHEEL
pyGPT_api-0.1.3.dist-info/top_level.txt
pyGPT_api-0.1.3.dist-info/RECORD
