Metadata-Version: 2.1
Name: pyGPT-api
Version: 0.1.3
Summary: An unofficial API allowing free interaction with ChatGPT in Python
Home-page: https://github.com/alfred-exe/pyGPT
Author: Alfred Tonic
Author-email: eldritch.alfred@outlook.com
License: GNU General Public License v2.0
Keywords: chatgpt,openai
Requires-Python: >=3.6
Requires-Dist: tls-client >=0.2.2
